shuttle/__main__.py
shuttle/lib.py
shuttle/local.py
shuttle_aws/__init__.py
shuttle_aws/rds.py
shuttle_aws/s3.py
shuttle_common/__init__.py
shuttle_infra/Dockerfile
shuttle_infra/__init__.py
shuttle_infra/build.py
shuttle_infra/cdk.py
shuttle_infra/cf.py
shuttle_infra/common.py
shuttle_runtime/__init__.py
shuttle_task/__init__.py
shuttle_cobra-0.1.3.dist-info/METADATA
shuttle_cobra-0.1.3.dist-info/WHEEL
shuttle_cobra-0.1.3.dist-info/entry_points.txt
shuttle_cobra-0.1.3.dist-info/licenses/LICENSE
shuttle_cobra-0.1.3.dist-info/RECORD
