Metadata-Version: 2.4
Name: shuttle-cobra
Version: 0.1.3
Summary: Shuttle inspired framework for Python
Project-URL: Homepage, https://shuttle.dev/
Project-URL: Documentation, https://docs.cobra.shuttle.dev/
Project-URL: Repository, https://github.com/shuttle-hq/shuttle-cobra/
Author: Shuttle Cobra contributors
Maintainer: Shuttle
License-File: LICENSE
Keywords: cli,cloud,data,deployment,devops,ifc,infrastructure
Classifier: Development Status :: 3 - Alpha
Classifier: Environment :: Console
Classifier: Intended Audience :: Developers
Classifier: License :: OSI Approved :: Apache Software License
Classifier: Natural Language :: English
Classifier: Operating System :: OS Independent
Classifier: Programming Language :: Python :: 3.12
Classifier: Topic :: System :: Software Distribution
Requires-Python: >=3.12
Requires-Dist: aws-cdk-lib>=2.132.0
Requires-Dist: boto3>=1.39.3
Requires-Dist: click>=8.2.1
Requires-Dist: docker>=7.1.0
Requires-Dist: pathspec>=0.12.1
Requires-Dist: psycopg2-binary>=2.9.10
Requires-Dist: pydantic>=2.11.7
Requires-Dist: ruff>=0.12.2
